polypoly/__init__.py
polypoly/data/dict.json
polypoly/data/high_freq_poly_words.txt
polypoly/data/proun_dict_tiny.txt
polypoly/data/tag.json
polypoly/data/tag.txt
polypoly/data/vocab.json
polypoly/data/vocab.txt
polypoly/data/words.txt
polypoly/savedModel/saved_model.pb
polypoly/savedModel/variables/variables.data-00000-of-00001
polypoly/savedModel/variables/variables.index
polypoly-0.0.3.dist-info/LICENSE
polypoly-0.0.3.dist-info/METADATA
polypoly-0.0.3.dist-info/WHEEL
polypoly-0.0.3.dist-info/top_level.txt
polypoly-0.0.3.dist-info/RECORD
